opensearchcli/__init__.py
opensearchcli/cli.py
opensearchcli/commands/__init__.py
opensearchcli/commands/cluster.py
opensearchcli/commands/cluster_settings.py
opensearchcli/commands/commands.py
opensearchcli/commands/config.py
opensearchcli/commands/exceptions.py
opensearchcli/commands/helpers.py
opensearchcli/commands/index.py
opensearchcli/commands/index_settings.py
opensearchcli/commands/raw.py
opensearchcli/commands/snapshot.py
opensearchcli-0.2.5.dist-info/METADATA
opensearchcli-0.2.5.dist-info/WHEEL
opensearchcli-0.2.5.dist-info/entry_points.txt
opensearchcli-0.2.5.dist-info/top_level.txt
opensearchcli-0.2.5.dist-info/RECORD
