Metadata-Version: 2.4
Name: opensearchcli
Version: 0.2.5
Summary: A CLI tool for OpenSearch
Requires-Python: <4,>=3.10
Requires-Dist: typer>=0.20.0
Requires-Dist: opensearch-py<4.0.0,>=3.1.0
Requires-Dist: tomlkit>=0.13.3
